dynAMMo/__init__.py
dynAMMo/base/__init__.py
dynAMMo/base/experiments.py
dynAMMo/base/msm.py
dynAMMo/base/static_amm.py
dynAMMo/manifold/__init__.py
dynAMMo/manifold/stiefel.py
dynAMMo/model/__init__.py
dynAMMo/model/estimator.py
dynAMMo/tools/__init__.py
dynAMMo/tools/definitions.py
dynAMMo/tools/plot.py
dynAMMo/tools/utils.py
dynAMMo-0.0.dist-info/LICENSE
dynAMMo-0.0.dist-info/METADATA
dynAMMo-0.0.dist-info/WHEEL
dynAMMo-0.0.dist-info/top_level.txt
dynAMMo-0.0.dist-info/RECORD
