Metadata-Version: 2.1
Name: dynAMMo
Version: 0.0
Summary: dynAMMo – dynamic Augmented Markov Models
Home-page: 
Author: Christopher Kolloff
Author-email: kolloff@chalmers.se
License: MIT
License-File: LICENSE
Requires-Dist: deeptime ==0.4.4
Requires-Dist: h5py ==3.9.0
Requires-Dist: matplotlib ==3.7.2
Requires-Dist: MDAnalysis ==2.7.0
Requires-Dist: mdtraj ==1.9.9
Requires-Dist: msmtools ==1.2.6
Requires-Dist: networkx ==3.2.1
Requires-Dist: numpy ==1.25.2
Requires-Dist: pandas ==2.0.3
Requires-Dist: pyemma ==2.5.12
Requires-Dist: scipy ==1.12.0
Requires-Dist: setuptools ==68.1.2
Requires-Dist: torch ==2.1.0
Requires-Dist: tqdm ==4.66.1
